{
   "etag": "\"MjAyMi0wNi0xMFQxMDozNjoyNS4zODBa\"",
   "items": [
      {
         "author": {
            "displayName": "Ray",
            "id": "15300513361551186188",
            "image": {
               "url": "//www.blogger.com/img/blogger_logo_round_35.png"
            },
            "url": "https://www.blogger.com/profile/15300513361551186188"
         },
         "blog": {
            "id": "8097677691848866160"
         },
         "content": "",
         "etag": "\"dGltZXN0YW1wOiAxNjU0ODU3Mzg1MzgwCm9mZnNldDogLTI1MjAwMDAwCg\"",
         "id": "5854290933909255537",
         "kind": "blogger#post",
         "published": "2022-06-10T03:36:00-07:00",
         "replies": {
            "selfLink": "https://www.googleapis.com/blogger/v3/blogs/8097677691848866160/posts/5854290933909255537/comments",
            "totalItems": "0"
         },
         "selfLink": "https://www.googleapis.com/blogger/v3/blogs/8097677691848866160/posts/5854290933909255537",
         "title": "Military doctrine",
         "updated": "2022-06-10T03:36:25-07:00",
         "url": "http://militarconceptoswiki.blogspot.com/2022/06/military-doctrine.html"
      },
      {
         "author": {
            "displayName": "Ray",
            "id": "15300513361551186188",
            "image": {
               "url": "//www.blogger.com/img/blogger_logo_round_35.png"
            },
            "url": "https://www.blogger.com/profile/15300513361551186188"
         },
         "blog": {
            "id": "8097677691848866160"
         },
         "content": "",
         "etag": "\"dGltZXN0YW1wOiAxNjU0ODU3MzIzODM1Cm9mZnNldDogLTI1MjAwMDAwCg\"",
         "id": "6196404286713994411",
         "kind": "blogger#post",
         "published": "2022-06-10T03:35:00-07:00",
         "replies": {
            "selfLink": "https://www.googleapis.com/blogger/v3/blogs/8097677691848866160/posts/6196404286713994411/comments",
            "totalItems": "0"
         },
         "selfLink": "https://www.googleapis.com/blogger/v3/blogs/8097677691848866160/posts/6196404286713994411",
         "title": "Principles of war",
         "updated": "2022-06-10T03:35:23-07:00",
         "url": "http://militarconceptoswiki.blogspot.com/2022/06/principles-of-war.html"
      },
      {
         "author": {
            "displayName": "Ray",
            "id": "15300513361551186188",
            "image": {
               "url": "//www.blogger.com/img/blogger_logo_round_35.png"
            },
            "url": "https://www.blogger.com/profile/15300513361551186188"
         },
         "blog": {
            "id": "8097677691848866160"
         },
         "content": "",
         "etag": "\"dGltZXN0YW1wOiAxNjU0ODU3MjQ5OTY0Cm9mZnNldDogLTI1MjAwMDAwCg\"",
         "id": "9151709362169327058",
         "kind": "blogger#post",
         "published": "2022-06-10T03:34:00-07:00",
         "replies": {
            "selfLink": "https://www.googleapis.com/blogger/v3/blogs/8097677691848866160/posts/9151709362169327058/comments",
            "totalItems": "0"
         },
         "selfLink": "https://www.googleapis.com/blogger/v3/blogs/8097677691848866160/posts/9151709362169327058",
         "title": "Military strategy",
         "updated": "2022-06-10T03:34:09-07:00",
         "url": "http://militarconceptoswiki.blogspot.com/2022/06/military-strategy.html"
      },
      {
         "author": {
            "displayName": "Ray",
            "id": "15300513361551186188",
            "image": {
               "url": "//www.blogger.com/img/blogger_logo_round_35.png"
            },
            "url": "https://www.blogger.com/profile/15300513361551186188"
         },
         "blog": {
            "id": "8097677691848866160"
         },
         "content": "",
         "etag": "\"dGltZXN0YW1wOiAxNjU0ODU3MTUwMDY4Cm9mZnNldDogLTI1MjAwMDAwCg\"",
         "id": "3256361447679810948",
         "kind": "blogger#post",
         "published": "2022-06-10T03:32:00-07:00",
         "replies": {
            "selfLink": "https://www.googleapis.com/blogger/v3/blogs/8097677691848866160/posts/3256361447679810948/comments",
            "totalItems": "0"
         },
         "selfLink": "https://www.googleapis.com/blogger/v3/blogs/8097677691848866160/posts/3256361447679810948",
         "title": "List of military strategi and concepts",
         "updated": "2022-06-10T03:32:30-07:00",
         "url": "http://militarconceptoswiki.blogspot.com/2022/06/list-of-military-strategi-and-concepts.html"
      },
      {
         "author": {
            "displayName": "Ray",
            "id": "15300513361551186188",
            "image": {
               "url": "//www.blogger.com/img/blogger_logo_round_35.png"
            },
            "url": "https://www.blogger.com/profile/15300513361551186188"
         },
         "blog": {
            "id": "8097677691848866160"
         },
         "content": "",
         "etag": "\"dGltZXN0YW1wOiAxNjU0ODU3MDc2OTQwCm9mZnNldDogLTI1MjAwMDAwCg\"",
         "id": "3554122894851011380",
         "kind": "blogger#post",
         "published": "2022-06-10T03:31:00-07:00",
         "replies": {
            "selfLink": "https://www.googleapis.com/blogger/v3/blogs/8097677691848866160/posts/3554122894851011380/comments",
            "totalItems": "0"
         },
         "selfLink": "https://www.googleapis.com/blogger/v3/blogs/8097677691848866160/posts/3554122894851011380",
         "title": "Strategic goal",
         "updated": "2022-06-10T03:31:16-07:00",
         "url": "http://militarconceptoswiki.blogspot.com/2022/06/strategic-goal.html"
      },
      {
         "author": {
            "displayName": "Ray",
            "id": "15300513361551186188",
            "image": {
               "url": "//www.blogger.com/img/blogger_logo_round_35.png"
            },
            "url": "https://www.blogger.com/profile/15300513361551186188"
         },
         "blog": {
            "id": "8097677691848866160"
         },
         "content": "",
         "etag": "\"dGltZXN0YW1wOiAxNjU0ODU3MDI1OTExCm9mZnNldDogLTI1MjAwMDAwCg\"",
         "id": "6943400168755847196",
         "kind": "blogger#post",
         "published": "2022-06-10T03:30:00-07:00",
         "replies": {
            "selfLink": "https://www.googleapis.com/blogger/v3/blogs/8097677691848866160/posts/6943400168755847196/comments",
            "totalItems": "0"
         },
         "selfLink": "https://www.googleapis.com/blogger/v3/blogs/8097677691848866160/posts/6943400168755847196",
         "title": "Grand strategy",
         "updated": "2022-06-10T03:30:25-07:00",
         "url": "http://militarconceptoswiki.blogspot.com/2022/06/grand-strategy.html"
      },
      {
         "author": {
            "displayName": "Ray",
            "id": "15300513361551186188",
            "image": {
               "url": "//www.blogger.com/img/blogger_logo_round_35.png"
            },
            "url": "https://www.blogger.com/profile/15300513361551186188"
         },
         "blog": {
            "id": "8097677691848866160"
         },
         "content": "",
         "etag": "\"dGltZXN0YW1wOiAxNjU0ODU2OTYzMDAyCm9mZnNldDogLTI1MjAwMDAwCg\"",
         "id": "8133309078270089637",
         "kind": "blogger#post",
         "published": "2022-06-10T03:29:00-07:00",
         "replies": {
            "selfLink": "https://www.googleapis.com/blogger/v3/blogs/8097677691848866160/posts/8133309078270089637/comments",
            "totalItems": "0"
         },
         "selfLink": "https://www.googleapis.com/blogger/v3/blogs/8097677691848866160/posts/8133309078270089637",
         "title": "Military logistics",
         "updated": "2022-06-10T03:29:23-07:00",
         "url": "http://militarconceptoswiki.blogspot.com/2022/06/military-logistics.html"
      },
      {
         "author": {
            "displayName": "Ray",
            "id": "15300513361551186188",
            "image": {
               "url": "//www.blogger.com/img/blogger_logo_round_35.png"
            },
            "url": "https://www.blogger.com/profile/15300513361551186188"
         },
         "blog": {
            "id": "8097677691848866160"
         },
         "content": "",
         "etag": "\"dGltZXN0YW1wOiAxNjU0ODU2ODgxMzI2Cm9mZnNldDogLTI1MjAwMDAwCg\"",
         "id": "807804964802394557",
         "kind": "blogger#post",
         "published": "2022-06-10T03:28:00-07:00",
         "replies": {
            "selfLink": "https://www.googleapis.com/blogger/v3/blogs/8097677691848866160/posts/807804964802394557/comments",
            "totalItems": "0"
         },
         "selfLink": "https://www.googleapis.com/blogger/v3/blogs/8097677691848866160/posts/807804964802394557",
         "title": "Military organization",
         "updated": "2022-06-10T03:28:01-07:00",
         "url": "http://militarconceptoswiki.blogspot.com/2022/06/military-organization.html"
      },
      {
         "author": {
            "displayName": "Ray",
            "id": "15300513361551186188",
            "image": {
               "url": "//www.blogger.com/img/blogger_logo_round_35.png"
            },
            "url": "https://www.blogger.com/profile/15300513361551186188"
         },
         "blog": {
            "id": "8097677691848866160"
         },
         "content": "",
         "etag": "\"dGltZXN0YW1wOiAxNjU0ODU2NjgzNTQ4Cm9mZnNldDogLTI1MjAwMDAwCg\"",
         "id": "6268318048719038555",
         "kind": "blogger#post",
         "published": "2022-06-10T03:24:00-07:00",
         "replies": {
            "selfLink": "https://www.googleapis.com/blogger/v3/blogs/8097677691848866160/posts/6268318048719038555/comments",
            "totalItems": "0"
         },
         "selfLink": "https://www.googleapis.com/blogger/v3/blogs/8097677691848866160/posts/6268318048719038555",
         "title": "Combat arms",
         "updated": "2022-06-10T03:24:43-07:00",
         "url": "http://militarconceptoswiki.blogspot.com/2022/06/combat-arms.html"
      },
      {
         "author": {
            "displayName": "Ray",
            "id": "15300513361551186188",
            "image": {
               "url": "//www.blogger.com/img/blogger_logo_round_35.png"
            },
            "url": "https://www.blogger.com/profile/15300513361551186188"
         },
         "blog": {
            "id": "8097677691848866160"
         },
         "content": "",
         "etag": "\"dGltZXN0YW1wOiAxNjU0ODU2NjI3NjY3Cm9mZnNldDogLTI1MjAwMDAwCg\"",
         "id": "7542663121235959568",
         "kind": "blogger#post",
         "published": "2022-06-10T03:23:00-07:00",
         "replies": {
            "selfLink": "https://www.googleapis.com/blogger/v3/blogs/8097677691848866160/posts/7542663121235959568/comments",
            "totalItems": "0"
         },
         "selfLink": "https://www.googleapis.com/blogger/v3/blogs/8097677691848866160/posts/7542663121235959568",
         "title": "Infantry",
         "updated": "2022-06-10T03:23:47-07:00",
         "url": "http://militarconceptoswiki.blogspot.com/2022/06/infantry.html"
      },
      {
         "author": {
            "displayName": "Ray",
            "id": "15300513361551186188",
            "image": {
               "url": "//www.blogger.com/img/blogger_logo_round_35.png"
            },
            "url": "https://www.blogger.com/profile/15300513361551186188"
         },
         "blog": {
            "id": "8097677691848866160"
         },
         "content": "",
         "etag": "\"dGltZXN0YW1wOiAxNjU0ODU2NDg4NTc3Cm9mZnNldDogLTI1MjAwMDAwCg\"",
         "id": "3755333466210819945",
         "kind": "blogger#post",
         "published": "2022-06-10T03:21:00-07:00",
         "replies": {
            "selfLink": "https://www.googleapis.com/blogger/v3/blogs/8097677691848866160/posts/3755333466210819945/comments",
            "totalItems": "0"
         },
         "selfLink": "https://www.googleapis.com/blogger/v3/blogs/8097677691848866160/posts/3755333466210819945",
         "title": "Light infantry",
         "updated": "2022-06-10T03:21:28-07:00",
         "url": "http://militarconceptoswiki.blogspot.com/2022/06/light-infantry.html"
      },
      {
         "author": {
            "displayName": "Ray",
            "id": "15300513361551186188",
            "image": {
               "url": "//www.blogger.com/img/blogger_logo_round_35.png"
            },
            "url": "https://www.blogger.com/profile/15300513361551186188"
         },
         "blog": {
            "id": "8097677691848866160"
         },
         "content": "",
         "etag": "\"dGltZXN0YW1wOiAxNjU0ODU2NDEzNTM2Cm9mZnNldDogLTI1MjAwMDAwCg\"",
         "id": "6930986170308096407",
         "kind": "blogger#post",
         "published": "2022-06-10T03:20:00-07:00",
         "replies": {
            "selfLink": "https://www.googleapis.com/blogger/v3/blogs/8097677691848866160/posts/6930986170308096407/comments",
            "totalItems": "0"
         },
         "selfLink": "https://www.googleapis.com/blogger/v3/blogs/8097677691848866160/posts/6930986170308096407",
         "title": "Combat support",
         "updated": "2022-06-10T03:20:13-07:00",
         "url": "http://militarconceptoswiki.blogspot.com/2022/06/combat-support.html"
      },
      {
         "author": {
            "displayName": "Ray",
            "id": "15300513361551186188",
            "image": {
               "url": "//www.blogger.com/img/blogger_logo_round_35.png"
            },
            "url": "https://www.blogger.com/profile/15300513361551186188"
         },
         "blog": {
            "id": "8097677691848866160"
         },
         "content": "",
         "etag": "\"dGltZXN0YW1wOiAxNjU0ODU2MzYzMzk0Cm9mZnNldDogLTI1MjAwMDAwCg\"",
         "id": "7529327305249437993",
         "kind": "blogger#post",
         "published": "2022-06-10T03:19:00-07:00",
         "replies": {
            "selfLink": "https://www.googleapis.com/blogger/v3/blogs/8097677691848866160/posts/7529327305249437993/comments",
            "totalItems": "0"
         },
         "selfLink": "https://www.googleapis.com/blogger/v3/blogs/8097677691848866160/posts/7529327305249437993",
         "title": "Cavalry",
         "updated": "2022-06-10T03:19:23-07:00",
         "url": "http://militarconceptoswiki.blogspot.com/2022/06/cavalry.html"
      },
      {
         "author": {
            "displayName": "Ray",
            "id": "15300513361551186188",
            "image": {
               "url": "//www.blogger.com/img/blogger_logo_round_35.png"
            },
            "url": "https://www.blogger.com/profile/15300513361551186188"
         },
         "blog": {
            "id": "8097677691848866160"
         },
         "content": "",
         "etag": "\"dGltZXN0YW1wOiAxNjU0ODU2MjIxNzcwCm9mZnNldDogLTI1MjAwMDAwCg\"",
         "id": "188294525852872912",
         "kind": "blogger#post",
         "published": "2022-06-10T03:17:00-07:00",
         "replies": {
            "selfLink": "https://www.googleapis.com/blogger/v3/blogs/8097677691848866160/posts/188294525852872912/comments",
            "totalItems": "0"
         },
         "selfLink": "https://www.googleapis.com/blogger/v3/blogs/8097677691848866160/posts/188294525852872912",
         "title": "Special forces",
         "updated": "2022-06-10T03:17:01-07:00",
         "url": "http://militarconceptoswiki.blogspot.com/2022/06/special-forces.html"
      },
      {
         "author": {
            "displayName": "Ray",
            "id": "15300513361551186188",
            "image": {
               "url": "//www.blogger.com/img/blogger_logo_round_35.png"
            },
            "url": "https://www.blogger.com/profile/15300513361551186188"
         },
         "blog": {
            "id": "8097677691848866160"
         },
         "content": "",
         "etag": "\"dGltZXN0YW1wOiAxNjU0ODU2MTQ4NjE3Cm9mZnNldDogLTI1MjAwMDAwCg\"",
         "id": "8422383266160202834",
         "kind": "blogger#post",
         "published": "2022-06-10T03:15:00-07:00",
         "replies": {
            "selfLink": "https://www.googleapis.com/blogger/v3/blogs/8097677691848866160/posts/8422383266160202834/comments",
            "totalItems": "0"
         },
         "selfLink": "https://www.googleapis.com/blogger/v3/blogs/8097677691848866160/posts/8422383266160202834",
         "title": "Artillery",
         "updated": "2022-06-10T03:15:48-07:00",
         "url": "http://militarconceptoswiki.blogspot.com/2022/06/artillery.html"
      },
      {
         "author": {
            "displayName": "Ray",
            "id": "15300513361551186188",
            "image": {
               "url": "//www.blogger.com/img/blogger_logo_round_35.png"
            },
            "url": "https://www.blogger.com/profile/15300513361551186188"
         },
         "blog": {
            "id": "8097677691848866160"
         },
         "content": "",
         "etag": "\"dGltZXN0YW1wOiAxNjU0ODU1NTQyNjIwCm9mZnNldDogLTI1MjAwMDAwCg\"",
         "id": "7807028821935348172",
         "kind": "blogger#post",
         "published": "2022-06-10T03:05:00-07:00",
         "replies": {
            "selfLink": "https://www.googleapis.com/blogger/v3/blogs/8097677691848866160/posts/7807028821935348172/comments",
            "totalItems": "0"
         },
         "selfLink": "https://www.googleapis.com/blogger/v3/blogs/8097677691848866160/posts/7807028821935348172",
         "title": "Operational level of war",
         "updated": "2022-06-10T03:05:42-07:00",
         "url": "http://militarconceptoswiki.blogspot.com/2022/06/operational-level-of-war.html"
      },
      {
         "author": {
            "displayName": "Ray",
            "id": "15300513361551186188",
            "image": {
               "url": "//www.blogger.com/img/blogger_logo_round_35.png"
            },
            "url": "https://www.blogger.com/profile/15300513361551186188"
         },
         "blog": {
            "id": "8097677691848866160"
         },
         "content": "",
         "etag": "\"dGltZXN0YW1wOiAxNjU0ODU1NDE2Mjc2Cm9mZnNldDogLTI1MjAwMDAwCg\"",
         "id": "3223105659789787869",
         "kind": "blogger#post",
         "published": "2022-06-10T03:03:00-07:00",
         "replies": {
            "selfLink": "https://www.googleapis.com/blogger/v3/blogs/8097677691848866160/posts/3223105659789787869/comments",
            "totalItems": "0"
         },
         "selfLink": "https://www.googleapis.com/blogger/v3/blogs/8097677691848866160/posts/3223105659789787869",
         "title": "Military tactics",
         "updated": "2022-06-10T03:03:36-07:00",
         "url": "http://militarconceptoswiki.blogspot.com/2022/06/military-tactics.html"
      },
      {
         "author": {
            "displayName": "Ray",
            "id": "15300513361551186188",
            "image": {
               "url": "//www.blogger.com/img/blogger_logo_round_35.png"
            },
            "url": "https://www.blogger.com/profile/15300513361551186188"
         },
         "blog": {
            "id": "8097677691848866160"
         },
         "content": "",
         "etag": "\"dGltZXN0YW1wOiAxNjU0ODU1MzMyNzI1Cm9mZnNldDogLTI1MjAwMDAwCg\"",
         "id": "6426459381913520429",
         "kind": "blogger#post",
         "published": "2022-06-10T03:02:00-07:00",
         "replies": {
            "selfLink": "https://www.googleapis.com/blogger/v3/blogs/8097677691848866160/posts/6426459381913520429/comments",
            "totalItems": "0"
         },
         "selfLink": "https://www.googleapis.com/blogger/v3/blogs/8097677691848866160/posts/6426459381913520429",
         "title": "List of military tactics",
         "updated": "2022-06-10T03:02:12-07:00",
         "url": "http://militarconceptoswiki.blogspot.com/2022/06/list-of-military-tactics.html"
      },
      {
         "author": {
            "displayName": "Ray",
            "id": "15300513361551186188",
            "image": {
               "url": "//www.blogger.com/img/blogger_logo_round_35.png"
            },
            "url": "https://www.blogger.com/profile/15300513361551186188"
         },
         "blog": {
            "id": "8097677691848866160"
         },
         "content": "",
         "etag": "\"dGltZXN0YW1wOiAxNjU0ODU1MzYxNDU2Cm9mZnNldDogLTI1MjAwMDAwCg\"",
         "id": "6993132510368611554",
         "kind": "blogger#post",
         "published": "2022-06-10T03:01:00-07:00",
         "replies": {
            "selfLink": "https://www.googleapis.com/blogger/v3/blogs/8097677691848866160/posts/6993132510368611554/comments",
            "totalItems": "0"
         },
         "selfLink": "https://www.googleapis.com/blogger/v3/blogs/8097677691848866160/posts/6993132510368611554",
         "title": "Force multiplication",
         "updated": "2022-06-10T03:02:41-07:00",
         "url": "http://militarconceptoswiki.blogspot.com/2022/06/foto-multiplication.html"
      },
      {
         "author": {
            "displayName": "Ray",
            "id": "15300513361551186188",
            "image": {
               "url": "//www.blogger.com/img/blogger_logo_round_35.png"
            },
            "url": "https://www.blogger.com/profile/15300513361551186188"
         },
         "blog": {
            "id": "8097677691848866160"
         },
         "content": "",
         "etag": "\"dGltZXN0YW1wOiAxNjU0ODMzMjkyNjM4Cm9mZnNldDogLTI1MjAwMDAwCg\"",
         "id": "6886158314116568328",
         "kind": "blogger#post",
         "published": "2022-06-09T20:54:00-07:00",
         "replies": {
            "selfLink": "https://www.googleapis.com/blogger/v3/blogs/8097677691848866160/posts/6886158314116568328/comments",
            "totalItems": "0"
         },
         "selfLink": "https://www.googleapis.com/blogger/v3/blogs/8097677691848866160/posts/6886158314116568328",
         "title": "Individual movement technique",
         "updated": "2022-06-09T20:54:52-07:00",
         "url": "http://militarconceptoswiki.blogspot.com/2022/06/individual-movement-technique.html"
      },
      {
         "author": {
            "displayName": "Ray",
            "id": "15300513361551186188",
            "image": {
               "url": "//www.blogger.com/img/blogger_logo_round_35.png"
            },
            "url": "https://www.blogger.com/profile/15300513361551186188"
         },
         "blog": {
            "id": "8097677691848866160"
         },
         "content": "",
         "etag": "\"dGltZXN0YW1wOiAxNjU0ODMzMjEwNjczCm9mZnNldDogLTI1MjAwMDAwCg\"",
         "id": "5014099506503844240",
         "kind": "blogger#post",
         "published": "2022-06-09T20:53:00-07:00",
         "replies": {
            "selfLink": "https://www.googleapis.com/blogger/v3/blogs/8097677691848866160/posts/5014099506503844240/comments",
            "totalItems": "0"
         },
         "selfLink": "https://www.googleapis.com/blogger/v3/blogs/8097677691848866160/posts/5014099506503844240",
         "title": "Fire and movement",
         "updated": "2022-06-09T20:53:30-07:00",
         "url": "http://militarconceptoswiki.blogspot.com/2022/06/fire-and-movement.html"
      },
      {
         "author": {
            "displayName": "Ray",
            "id": "15300513361551186188",
            "image": {
               "url": "//www.blogger.com/img/blogger_logo_round_35.png"
            },
            "url": "https://www.blogger.com/profile/15300513361551186188"
         },
         "blog": {
            "id": "8097677691848866160"
         },
         "content": "",
         "etag": "\"dGltZXN0YW1wOiAxNjU0ODMzMTY0MzIzCm9mZnNldDogLTI1MjAwMDAwCg\"",
         "id": "5914540251667284734",
         "kind": "blogger#post",
         "published": "2022-06-09T20:52:00-07:00",
         "replies": {
            "selfLink": "https://www.googleapis.com/blogger/v3/blogs/8097677691848866160/posts/5914540251667284734/comments",
            "totalItems": "0"
         },
         "selfLink": "https://www.googleapis.com/blogger/v3/blogs/8097677691848866160/posts/5914540251667284734",
         "title": "Hulldown",
         "updated": "2022-06-09T20:52:44-07:00",
         "url": "http://militarconceptoswiki.blogspot.com/2022/06/hulldown.html"
      },
      {
         "author": {
            "displayName": "Ray",
            "id": "15300513361551186188",
            "image": {
               "url": "//www.blogger.com/img/blogger_logo_round_35.png"
            },
            "url": "https://www.blogger.com/profile/15300513361551186188"
         },
         "blog": {
            "id": "8097677691848866160"
         },
         "content": "",
         "etag": "\"dGltZXN0YW1wOiAxNjU0ODMzMTA5OTQ3Cm9mZnNldDogLTI1MjAwMDAwCg\"",
         "id": "6930077146763602677",
         "kind": "blogger#post",
         "published": "2022-06-09T20:51:00-07:00",
         "replies": {
            "selfLink": "https://www.googleapis.com/blogger/v3/blogs/8097677691848866160/posts/6930077146763602677/comments",
            "totalItems": "0"
         },
         "selfLink": "https://www.googleapis.com/blogger/v3/blogs/8097677691848866160/posts/6930077146763602677",
         "title": "Shoot and scoot",
         "updated": "2022-06-09T20:51:49-07:00",
         "url": "http://militarconceptoswiki.blogspot.com/2022/06/shoot-and-scoot.html"
      },
      {
         "author": {
            "displayName": "Ray",
            "id": "15300513361551186188",
            "image": {
               "url": "//www.blogger.com/img/blogger_logo_round_35.png"
            },
            "url": "https://www.blogger.com/profile/15300513361551186188"
         },
         "blog": {
            "id": "8097677691848866160"
         },
         "content": "",
         "etag": "\"dGltZXN0YW1wOiAxNjU0ODMzMDUwODc2Cm9mZnNldDogLTI1MjAwMDAwCg\"",
         "id": "8948267087738822380",
         "kind": "blogger#post",
         "published": "2022-06-09T20:50:00-07:00",
         "replies": {
            "selfLink": "https://www.googleapis.com/blogger/v3/blogs/8097677691848866160/posts/8948267087738822380/comments",
            "totalItems": "0"
         },
         "selfLink": "https://www.googleapis.com/blogger/v3/blogs/8097677691848866160/posts/8948267087738822380",
         "title": "Infiltration tactic",
         "updated": "2022-06-09T20:50:50-07:00",
         "url": "http://militarconceptoswiki.blogspot.com/2022/06/infiltration-tactic.html"
      },
      {
         "author": {
            "displayName": "Ray",
            "id": "15300513361551186188",
            "image": {
               "url": "//www.blogger.com/img/blogger_logo_round_35.png"
            },
            "url": "https://www.blogger.com/profile/15300513361551186188"
         },
         "blog": {
            "id": "8097677691848866160"
         },
         "content": "",
         "etag": "\"dGltZXN0YW1wOiAxNjU0ODMyOTc3NDEwCm9mZnNldDogLTI1MjAwMDAwCg\"",
         "id": "2355873002139207227",
         "kind": "blogger#post",
         "published": "2022-06-09T20:49:00-07:00",
         "replies": {
            "selfLink": "https://www.googleapis.com/blogger/v3/blogs/8097677691848866160/posts/2355873002139207227/comments",
            "totalItems": "0"
         },
         "selfLink": "https://www.googleapis.com/blogger/v3/blogs/8097677691848866160/posts/2355873002139207227",
         "title": "Marching fire",
         "updated": "2022-06-09T20:49:37-07:00",
         "url": "http://militarconceptoswiki.blogspot.com/2022/06/marching-fire.html"
      },
      {
         "author": {
            "displayName": "Ray",
            "id": "15300513361551186188",
            "image": {
               "url": "//www.blogger.com/img/blogger_logo_round_35.png"
            },
            "url": "https://www.blogger.com/profile/15300513361551186188"
         },
         "blog": {
            "id": "8097677691848866160"
         },
         "content": "",
         "etag": "\"dGltZXN0YW1wOiAxNjU0ODMyOTE1OTA0Cm9mZnNldDogLTI1MjAwMDAwCg\"",
         "id": "7489089674775401550",
         "kind": "blogger#post",
         "published": "2022-06-09T20:48:00-07:00",
         "replies": {
            "selfLink": "https://www.googleapis.com/blogger/v3/blogs/8097677691848866160/posts/7489089674775401550/comments",
            "totalItems": "0"
         },
         "selfLink": "https://www.googleapis.com/blogger/v3/blogs/8097677691848866160/posts/7489089674775401550",
         "title": "Overwatch",
         "updated": "2022-06-09T20:48:35-07:00",
         "url": "http://militarconceptoswiki.blogspot.com/2022/06/overwatch.html"
      },
      {
         "author": {
            "displayName": "Ray",
            "id": "15300513361551186188",
            "image": {
               "url": "//www.blogger.com/img/blogger_logo_round_35.png"
            },
            "url": "https://www.blogger.com/profile/15300513361551186188"
         },
         "blog": {
            "id": "8097677691848866160"
         },
         "content": "",
         "etag": "\"dGltZXN0YW1wOiAxNjU0ODMyNzExMzMxCm9mZnNldDogLTI1MjAwMDAwCg\"",
         "id": "1020872405009436188",
         "kind": "blogger#post",
         "published": "2022-06-09T20:45:00-07:00",
         "replies": {
            "selfLink": "https://www.googleapis.com/blogger/v3/blogs/8097677691848866160/posts/1020872405009436188/comments",
            "totalItems": "0"
         },
         "selfLink": "https://www.googleapis.com/blogger/v3/blogs/8097677691848866160/posts/1020872405009436188",
         "title": "Patrolling",
         "updated": "2022-06-09T20:45:11-07:00",
         "url": "http://militarconceptoswiki.blogspot.com/2022/06/patrolling.html"
      },
      {
         "author": {
            "displayName": "Ray",
            "id": "15300513361551186188",
            "image": {
               "url": "//www.blogger.com/img/blogger_logo_round_35.png"
            },
            "url": "https://www.blogger.com/profile/15300513361551186188"
         },
         "blog": {
            "id": "8097677691848866160"
         },
         "content": "",
         "etag": "\"dGltZXN0YW1wOiAxNjU0ODMyNTE1NTE3Cm9mZnNldDogLTI1MjAwMDAwCg\"",
         "id": "5544180087785271010",
         "kind": "blogger#post",
         "published": "2022-06-09T20:41:00-07:00",
         "replies": {
            "selfLink": "https://www.googleapis.com/blogger/v3/blogs/8097677691848866160/posts/5544180087785271010/comments",
            "totalItems": "0"
         },
         "selfLink": "https://www.googleapis.com/blogger/v3/blogs/8097677691848866160/posts/5544180087785271010",
         "title": "Ambush",
         "updated": "2022-06-09T20:41:55-07:00",
         "url": "http://militarconceptoswiki.blogspot.com/2022/06/ambush.html"
      },
      {
         "author": {
            "displayName": "Ray",
            "id": "15300513361551186188",
            "image": {
               "url": "//www.blogger.com/img/blogger_logo_round_35.png"
            },
            "url": "https://www.blogger.com/profile/15300513361551186188"
         },
         "blog": {
            "id": "8097677691848866160"
         },
         "content": "",
         "etag": "\"dGltZXN0YW1wOiAxNjU0ODMyNDY2NjE5Cm9mZnNldDogLTI1MjAwMDAwCg\"",
         "id": "3567822101713399201",
         "kind": "blogger#post",
         "published": "2022-06-09T20:41:00-07:00",
         "replies": {
            "selfLink": "https://www.googleapis.com/blogger/v3/blogs/8097677691848866160/posts/3567822101713399201/comments",
            "totalItems": "0"
         },
         "selfLink": "https://www.googleapis.com/blogger/v3/blogs/8097677691848866160/posts/3567822101713399201",
         "title": "Guerrilla warfare",
         "updated": "2022-06-09T20:41:06-07:00",
         "url": "http://militarconceptoswiki.blogspot.com/2022/06/guerrilla-warfare.html"
      },
      {
         "author": {
            "displayName": "Ray",
            "id": "15300513361551186188",
            "image": {
               "url": "//www.blogger.com/img/blogger_logo_round_35.png"
            },
            "url": "https://www.blogger.com/profile/15300513361551186188"
         },
         "blog": {
            "id": "8097677691848866160"
         },
         "content": "",
         "etag": "\"dGltZXN0YW1wOiAxNjU0ODMyMzYyNjQzCm9mZnNldDogLTI1MjAwMDAwCg\"",
         "id": "3188156670995493326",
         "kind": "blogger#post",
         "published": "2022-06-09T20:39:00-07:00",
         "replies": {
            "selfLink": "https://www.googleapis.com/blogger/v3/blogs/8097677691848866160/posts/3188156670995493326/comments",
            "totalItems": "0"
         },
         "selfLink": "https://www.googleapis.com/blogger/v3/blogs/8097677691848866160/posts/3188156670995493326",
         "title": "Asymmetric warfare",
         "updated": "2022-06-09T20:39:22-07:00",
         "url": "http://militarconceptoswiki.blogspot.com/2022/06/asymmetric-warfare.html"
      },
      {
         "author": {
            "displayName": "Ray",
            "id": "15300513361551186188",
            "image": {
               "url": "//www.blogger.com/img/blogger_logo_round_35.png"
            },
            "url": "https://www.blogger.com/profile/15300513361551186188"
         },
         "blog": {
            "id": "8097677691848866160"
         },
         "content": "",
         "etag": "\"dGltZXN0YW1wOiAxNjU0ODMyMjUxMTUwCm9mZnNldDogLTI1MjAwMDAwCg\"",
         "id": "5557277943527808819",
         "kind": "blogger#post",
         "published": "2022-06-09T20:37:00-07:00",
         "replies": {
            "selfLink": "https://www.googleapis.com/blogger/v3/blogs/8097677691848866160/posts/5557277943527808819/comments",
            "totalItems": "0"
         },
         "selfLink": "https://www.googleapis.com/blogger/v3/blogs/8097677691848866160/posts/5557277943527808819",
         "title": "Charge (warfare)",
         "updated": "2022-06-09T20:37:31-07:00",
         "url": "http://militarconceptoswiki.blogspot.com/2022/06/charge-warfare.html"
      },
      {
         "author": {
            "displayName": "Ray",
            "id": "15300513361551186188",
            "image": {
               "url": "//www.blogger.com/img/blogger_logo_round_35.png"
            },
            "url": "https://www.blogger.com/profile/15300513361551186188"
         },
         "blog": {
            "id": "8097677691848866160"
         },
         "content": "",
         "etag": "\"dGltZXN0YW1wOiAxNjU0ODMyMTc4NjQ5Cm9mZnNldDogLTI1MjAwMDAwCg\"",
         "id": "906181492566348784",
         "kind": "blogger#post",
         "published": "2022-06-09T20:36:00-07:00",
         "replies": {
            "selfLink": "https://www.googleapis.com/blogger/v3/blogs/8097677691848866160/posts/906181492566348784/comments",
            "totalItems": "0"
         },
         "selfLink": "https://www.googleapis.com/blogger/v3/blogs/8097677691848866160/posts/906181492566348784",
         "title": "Skirmisher",
         "updated": "2022-06-09T20:36:18-07:00",
         "url": "http://militarconceptoswiki.blogspot.com/2022/06/skirmisher.html"
      },
      {
         "author": {
            "displayName": "Ray",
            "id": "15300513361551186188",
            "image": {
               "url": "//www.blogger.com/img/blogger_logo_round_35.png"
            },
            "url": "https://www.blogger.com/profile/15300513361551186188"
         },
         "blog": {
            "id": "8097677691848866160"
         },
         "content": "",
         "etag": "\"dGltZXN0YW1wOiAxNjU0ODMyMTEyMTQwCm9mZnNldDogLTI1MjAwMDAwCg\"",
         "id": "3714055157880835041",
         "kind": "blogger#post",
         "published": "2022-06-09T20:35:00-07:00",
         "replies": {
            "selfLink": "https://www.googleapis.com/blogger/v3/blogs/8097677691848866160/posts/3714055157880835041/comments",
            "totalItems": "0"
         },
         "selfLink": "https://www.googleapis.com/blogger/v3/blogs/8097677691848866160/posts/3714055157880835041",
         "title": "Peaceful penetration",
         "updated": "2022-06-09T20:35:12-07:00",
         "url": "http://militarconceptoswiki.blogspot.com/2022/06/peaceful-penetration.html"
      },
      {
         "author": {
            "displayName": "Ray",
            "id": "15300513361551186188",
            "image": {
               "url": "//www.blogger.com/img/blogger_logo_round_35.png"
            },
            "url": "https://www.blogger.com/profile/15300513361551186188"
         },
         "blog": {
            "id": "8097677691848866160"
         },
         "content": "",
         "etag": "\"dGltZXN0YW1wOiAxNjU0ODMyMDQzNDk0Cm9mZnNldDogLTI1MjAwMDAwCg\"",
         "id": "2633921005821110754",
         "kind": "blogger#post",
         "published": "2022-06-09T20:34:00-07:00",
         "replies": {
            "selfLink": "https://www.googleapis.com/blogger/v3/blogs/8097677691848866160/posts/2633921005821110754/comments",
            "totalItems": "0"
         },
         "selfLink": "https://www.googleapis.com/blogger/v3/blogs/8097677691848866160/posts/2633921005821110754",
         "title": "Shock tactic",
         "updated": "2022-06-09T20:34:03-07:00",
         "url": "http://militarconceptoswiki.blogspot.com/2022/06/shock-tactic.html"
      },
      {
         "author": {
            "displayName": "Ray",
            "id": "15300513361551186188",
            "image": {
               "url": "//www.blogger.com/img/blogger_logo_round_35.png"
            },
            "url": "https://www.blogger.com/profile/15300513361551186188"
         },
         "blog": {
            "id": "8097677691848866160"
         },
         "content": "",
         "etag": "\"dGltZXN0YW1wOiAxNjU0ODMxOTg3NTA0Cm9mZnNldDogLTI1MjAwMDAwCg\"",
         "id": "6994258698932245713",
         "kind": "blogger#post",
         "published": "2022-06-09T20:33:00-07:00",
         "replies": {
            "selfLink": "https://www.googleapis.com/blogger/v3/blogs/8097677691848866160/posts/6994258698932245713/comments",
            "totalItems": "0"
         },
         "selfLink": "https://www.googleapis.com/blogger/v3/blogs/8097677691848866160/posts/6994258698932245713",
         "title": "Swarming (military)",
         "updated": "2022-06-09T20:33:07-07:00",
         "url": "http://militarconceptoswiki.blogspot.com/2022/06/swarming-military.html"
      },
      {
         "author": {
            "displayName": "Ray",
            "id": "15300513361551186188",
            "image": {
               "url": "//www.blogger.com/img/blogger_logo_round_35.png"
            },
            "url": "https://www.blogger.com/profile/15300513361551186188"
         },
         "blog": {
            "id": "8097677691848866160"
         },
         "content": "",
         "etag": "\"dGltZXN0YW1wOiAxNjU0ODMxOTIxNTQ3Cm9mZnNldDogLTI1MjAwMDAwCg\"",
         "id": "3978731676832242530",
         "kind": "blogger#post",
         "published": "2022-06-09T20:32:00-07:00",
         "replies": {
            "selfLink": "https://www.googleapis.com/blogger/v3/blogs/8097677691848866160/posts/3978731676832242530/comments",
            "totalItems": "0"
         },
         "selfLink": "https://www.googleapis.com/blogger/v3/blogs/8097677691848866160/posts/3978731676832242530",
         "title": "Pincer movement",
         "updated": "2022-06-09T20:32:01-07:00",
         "url": "http://militarconceptoswiki.blogspot.com/2022/06/pincer-movement.html"
      },
      {
         "author": {
            "displayName": "Ray",
            "id": "15300513361551186188",
            "image": {
               "url": "//www.blogger.com/img/blogger_logo_round_35.png"
            },
            "url": "https://www.blogger.com/profile/15300513361551186188"
         },
         "blog": {
            "id": "8097677691848866160"
         },
         "content": "",
         "etag": "\"dGltZXN0YW1wOiAxNjU0ODMxODYwMTU0Cm9mZnNldDogLTI1MjAwMDAwCg\"",
         "id": "4377188248727043015",
         "kind": "blogger#post",
         "published": "2022-06-09T20:31:00-07:00",
         "replies": {
            "selfLink": "https://www.googleapis.com/blogger/v3/blogs/8097677691848866160/posts/4377188248727043015/comments",
            "totalItems": "0"
         },
         "selfLink": "https://www.googleapis.com/blogger/v3/blogs/8097677691848866160/posts/4377188248727043015",
         "title": "Frontal assault",
         "updated": "2022-06-09T20:31:00-07:00",
         "url": "http://militarconceptoswiki.blogspot.com/2022/06/frontal-assault.html"
      },
      {
         "author": {
            "displayName": "Ray",
            "id": "15300513361551186188",
            "image": {
               "url": "//www.blogger.com/img/blogger_logo_round_35.png"
            },
            "url": "https://www.blogger.com/profile/15300513361551186188"
         },
         "blog": {
            "id": "8097677691848866160"
         },
         "content": "",
         "etag": "\"dGltZXN0YW1wOiAxNjU0ODMxODE0NDUxCm9mZnNldDogLTI1MjAwMDAwCg\"",
         "id": "8286118926517265664",
         "kind": "blogger#post",
         "published": "2022-06-09T20:30:00-07:00",
         "replies": {
            "selfLink": "https://www.googleapis.com/blogger/v3/blogs/8097677691848866160/posts/8286118926517265664/comments",
            "totalItems": "0"
         },
         "selfLink": "https://www.googleapis.com/blogger/v3/blogs/8097677691848866160/posts/8286118926517265664",
         "title": "Inverted wedge",
         "updated": "2022-06-09T20:30:14-07:00",
         "url": "http://militarconceptoswiki.blogspot.com/2022/06/inverted-wedge.html"
      },
      {
         "author": {
            "displayName": "Ray",
            "id": "15300513361551186188",
            "image": {
               "url": "//www.blogger.com/img/blogger_logo_round_35.png"
            },
            "url": "https://www.blogger.com/profile/15300513361551186188"
         },
         "blog": {
            "id": "8097677691848866160"
         },
         "content": "",
         "etag": "\"dGltZXN0YW1wOiAxNjU0ODMxMTcwNDY2Cm9mZnNldDogLTI1MjAwMDAwCg\"",
         "id": "1112677332847833478",
         "kind": "blogger#post",
         "published": "2022-06-09T20:19:00-07:00",
         "replies": {
            "selfLink": "https://www.googleapis.com/blogger/v3/blogs/8097677691848866160/posts/1112677332847833478/comments",
            "totalItems": "0"
         },
         "selfLink": "https://www.googleapis.com/blogger/v3/blogs/8097677691848866160/posts/1112677332847833478",
         "title": "Hammer and anvil",
         "updated": "2022-06-09T20:19:30-07:00",
         "url": "http://militarconceptoswiki.blogspot.com/2022/06/hammer-and-anvil.html"
      },
      {
         "author": {
            "displayName": "Ray",
            "id": "15300513361551186188",
            "image": {
               "url": "//www.blogger.com/img/blogger_logo_round_35.png"
            },
            "url": "https://www.blogger.com/profile/15300513361551186188"
         },
         "blog": {
            "id": "8097677691848866160"
         },
         "content": "",
         "etag": "\"dGltZXN0YW1wOiAxNjU0ODMxMTA0NjcxCm9mZnNldDogLTI1MjAwMDAwCg\"",
         "id": "4373458706019363534",
         "kind": "blogger#post",
         "published": "2022-06-09T20:18:00-07:00",
         "replies": {
            "selfLink": "https://www.googleapis.com/blogger/v3/blogs/8097677691848866160/posts/4373458706019363534/comments",
            "totalItems": "0"
         },
         "selfLink": "https://www.googleapis.com/blogger/v3/blogs/8097677691848866160/posts/4373458706019363534",
         "title": "Encirclement",
         "updated": "2022-06-09T20:18:24-07:00",
         "url": "http://militarconceptoswiki.blogspot.com/2022/06/encirclement.html"
      },
      {
         "author": {
            "displayName": "Ray",
            "id": "15300513361551186188",
            "image": {
               "url": "//www.blogger.com/img/blogger_logo_round_35.png"
            },
            "url": "https://www.blogger.com/profile/15300513361551186188"
         },
         "blog": {
            "id": "8097677691848866160"
         },
         "content": "",
         "etag": "\"dGltZXN0YW1wOiAxNjU0ODMxMDQ2NDgwCm9mZnNldDogLTI1MjAwMDAwCg\"",
         "id": "7323463165984959123",
         "kind": "blogger#post",
         "published": "2022-06-09T20:17:00-07:00",
         "replies": {
            "selfLink": "https://www.googleapis.com/blogger/v3/blogs/8097677691848866160/posts/7323463165984959123/comments",
            "totalItems": "0"
         },
         "selfLink": "https://www.googleapis.com/blogger/v3/blogs/8097677691848866160/posts/7323463165984959123",
         "title": "Armored spearhead",
         "updated": "2022-06-09T20:17:26-07:00",
         "url": "http://militarconceptoswiki.blogspot.com/2022/06/armored-spearhead.html"
      },
      {
         "author": {
            "displayName": "Ray",
            "id": "15300513361551186188",
            "image": {
               "url": "//www.blogger.com/img/blogger_logo_round_35.png"
            },
            "url": "https://www.blogger.com/profile/15300513361551186188"
         },
         "blog": {
            "id": "8097677691848866160"
         },
         "content": "",
         "etag": "\"dGltZXN0YW1wOiAxNjU0ODMxMDAxOTM5Cm9mZnNldDogLTI1MjAwMDAwCg\"",
         "id": "2555624149088587430",
         "kind": "blogger#post",
         "published": "2022-06-09T20:16:00-07:00",
         "replies": {
            "selfLink": "https://www.googleapis.com/blogger/v3/blogs/8097677691848866160/posts/2555624149088587430/comments",
            "totalItems": "0"
         },
         "selfLink": "https://www.googleapis.com/blogger/v3/blogs/8097677691848866160/posts/2555624149088587430",
         "title": "Flying wedge",
         "updated": "2022-06-09T20:16:41-07:00",
         "url": "http://militarconceptoswiki.blogspot.com/2022/06/flying-wedge.html"
      },
      {
         "author": {
            "displayName": "Ray",
            "id": "15300513361551186188",
            "image": {
               "url": "//www.blogger.com/img/blogger_logo_round_35.png"
            },
            "url": "https://www.blogger.com/profile/15300513361551186188"
         },
         "blog": {
            "id": "8097677691848866160"
         },
         "content": "",
         "etag": "\"dGltZXN0YW1wOiAxNjU0ODMwOTA3NTQzCm9mZnNldDogLTI1MjAwMDAwCg\"",
         "id": "3256724699979977602",
         "kind": "blogger#post",
         "published": "2022-06-09T20:15:00-07:00",
         "replies": {
            "selfLink": "https://www.googleapis.com/blogger/v3/blogs/8097677691848866160/posts/3256724699979977602/comments",
            "totalItems": "0"
         },
         "selfLink": "https://www.googleapis.com/blogger/v3/blogs/8097677691848866160/posts/3256724699979977602",
         "title": "Base of fire",
         "updated": "2022-06-09T20:15:07-07:00",
         "url": "http://militarconceptoswiki.blogspot.com/2022/06/base-of-fire.html"
      },
      {
         "author": {
            "displayName": "Ray",
            "id": "15300513361551186188",
            "image": {
               "url": "//www.blogger.com/img/blogger_logo_round_35.png"
            },
            "url": "https://www.blogger.com/profile/15300513361551186188"
         },
         "blog": {
            "id": "8097677691848866160"
         },
         "content": "",
         "etag": "\"dGltZXN0YW1wOiAxNjU0ODMwODY1NzM2Cm9mZnNldDogLTI1MjAwMDAwCg\"",
         "id": "4780621881148243970",
         "kind": "blogger#post",
         "published": "2022-06-09T20:14:00-07:00",
         "replies": {
            "selfLink": "https://www.googleapis.com/blogger/v3/blogs/8097677691848866160/posts/4780621881148243970/comments",
            "totalItems": "0"
         },
         "selfLink": "https://www.googleapis.com/blogger/v3/blogs/8097677691848866160/posts/4780621881148243970",
         "title": "Fire support",
         "updated": "2022-06-09T20:14:25-07:00",
         "url": "http://militarconceptoswiki.blogspot.com/2022/06/fire-support.html"
      },
      {
         "author": {
            "displayName": "Ray",
            "id": "15300513361551186188",
            "image": {
               "url": "//www.blogger.com/img/blogger_logo_round_35.png"
            },
            "url": "https://www.blogger.com/profile/15300513361551186188"
         },
         "blog": {
            "id": "8097677691848866160"
         },
         "content": "",
         "etag": "\"dGltZXN0YW1wOiAxNjU0ODMwODE3MzA0Cm9mZnNldDogLTI1MjAwMDAwCg\"",
         "id": "3204477093254405323",
         "kind": "blogger#post",
         "published": "2022-06-09T20:13:00-07:00",
         "replies": {
            "selfLink": "https://www.googleapis.com/blogger/v3/blogs/8097677691848866160/posts/3204477093254405323/comments",
            "totalItems": "0"
         },
         "selfLink": "https://www.googleapis.com/blogger/v3/blogs/8097677691848866160/posts/3204477093254405323",
         "title": "Flanking maneuver",
         "updated": "2022-06-09T20:13:37-07:00",
         "url": "http://militarconceptoswiki.blogspot.com/2022/06/flanking-maneuver.html"
      },
      {
         "author": {
            "displayName": "Ray",
            "id": "15300513361551186188",
            "image": {
               "url": "//www.blogger.com/img/blogger_logo_round_35.png"
            },
            "url": "https://www.blogger.com/profile/15300513361551186188"
         },
         "blog": {
            "id": "8097677691848866160"
         },
         "content": "",
         "etag": "\"dGltZXN0YW1wOiAxNjU0ODMwNzU0NzM5Cm9mZnNldDogLTI1MjAwMDAwCg\"",
         "id": "5074938750068339011",
         "kind": "blogger#post",
         "published": "2022-06-09T20:12:00-07:00",
         "replies": {
            "selfLink": "https://www.googleapis.com/blogger/v3/blogs/8097677691848866160/posts/5074938750068339011/comments",
            "totalItems": "0"
         },
         "selfLink": "https://www.googleapis.com/blogger/v3/blogs/8097677691848866160/posts/5074938750068339011",
         "title": "Interdiction",
         "updated": "2022-06-09T20:12:34-07:00",
         "url": "http://militarconceptoswiki.blogspot.com/2022/06/interdiction.html"
      },
      {
         "author": {
            "displayName": "Ray",
            "id": "15300513361551186188",
            "image": {
               "url": "//www.blogger.com/img/blogger_logo_round_35.png"
            },
            "url": "https://www.blogger.com/profile/15300513361551186188"
         },
         "blog": {
            "id": "8097677691848866160"
         },
         "content": "",
         "etag": "\"dGltZXN0YW1wOiAxNjU0ODMwNzExOTM4Cm9mZnNldDogLTI1MjAwMDAwCg\"",
         "id": "3528925540399981399",
         "kind": "blogger#post",
         "published": "2022-06-09T20:11:00-07:00",
         "replies": {
            "selfLink": "https://www.googleapis.com/blogger/v3/blogs/8097677691848866160/posts/3528925540399981399/comments",
            "totalItems": "0"
         },
         "selfLink": "https://www.googleapis.com/blogger/v3/blogs/8097677691848866160/posts/3528925540399981399",
         "title": "Siege",
         "updated": "2022-06-09T20:11:51-07:00",
         "url": "http://militarconceptoswiki.blogspot.com/2022/06/siege.html"
      },
      {
         "author": {
            "displayName": "Ray",
            "id": "15300513361551186188",
            "image": {
               "url": "//www.blogger.com/img/blogger_logo_round_35.png"
            },
            "url": "https://www.blogger.com/profile/15300513361551186188"
         },
         "blog": {
            "id": "8097677691848866160"
         },
         "content": "",
         "etag": "\"dGltZXN0YW1wOiAxNjU0ODMwNjIzMjIwCm9mZnNldDogLTI1MjAwMDAwCg\"",
         "id": "5397095966710889392",
         "kind": "blogger#post",
         "published": "2022-06-09T20:10:00-07:00",
         "replies": {
            "selfLink": "https://www.googleapis.com/blogger/v3/blogs/8097677691848866160/posts/5397095966710889392/comments",
            "totalItems": "0"
         },
         "selfLink": "https://www.googleapis.com/blogger/v3/blogs/8097677691848866160/posts/5397095966710889392",
         "title": "Air assault",
         "updated": "2022-06-09T20:10:23-07:00",
         "url": "http://militarconceptoswiki.blogspot.com/2022/06/air-assault.html"
      },
      {
         "author": {
            "displayName": "Ray",
            "id": "15300513361551186188",
            "image": {
               "url": "//www.blogger.com/img/blogger_logo_round_35.png"
            },
            "url": "https://www.blogger.com/profile/15300513361551186188"
         },
         "blog": {
            "id": "8097677691848866160"
         },
         "content": "",
         "etag": "\"dGltZXN0YW1wOiAxNjU0ODMwNTU4Mjg0Cm9mZnNldDogLTI1MjAwMDAwCg\"",
         "id": "4536431187779378913",
         "kind": "blogger#post",
         "published": "2022-06-09T20:09:00-07:00",
         "replies": {
            "selfLink": "https://www.googleapis.com/blogger/v3/blogs/8097677691848866160/posts/4536431187779378913/comments",
            "totalItems": "0"
         },
         "selfLink": "https://www.googleapis.com/blogger/v3/blogs/8097677691848866160/posts/4536431187779378913",
         "title": "Salient (military)",
         "updated": "2022-06-09T20:09:18-07:00",
         "url": "http://militarconceptoswiki.blogspot.com/2022/06/salient-military.html"
      },
      {
         "author": {
            "displayName": "Ray",
            "id": "15300513361551186188",
            "image": {
               "url": "//www.blogger.com/img/blogger_logo_round_35.png"
            },
            "url": "https://www.blogger.com/profile/15300513361551186188"
         },
         "blog": {
            "id": "8097677691848866160"
         },
         "content": "",
         "etag": "\"dGltZXN0YW1wOiAxNjU0ODMwNTA2Mjc3Cm9mZnNldDogLTI1MjAwMDAwCg\"",
         "id": "769022323153927585",
         "kind": "blogger#post",
         "published": "2022-06-09T20:08:00-07:00",
         "replies": {
            "selfLink": "https://www.googleapis.com/blogger/v3/blogs/8097677691848866160/posts/769022323153927585/comments",
            "totalItems": "0"
         },
         "selfLink": "https://www.googleapis.com/blogger/v3/blogs/8097677691848866160/posts/769022323153927585",
         "title": "Raid (military)",
         "updated": "2022-06-09T20:08:26-07:00",
         "url": "http://militarconceptoswiki.blogspot.com/2022/06/raid-military.html"
      },
      {
         "author": {
            "displayName": "Ray",
            "id": "15300513361551186188",
            "image": {
               "url": "//www.blogger.com/img/blogger_logo_round_35.png"
            },
            "url": "https://www.blogger.com/profile/15300513361551186188"
         },
         "blog": {
            "id": "8097677691848866160"
         },
         "content": "",
         "etag": "\"dGltZXN0YW1wOiAxNjU0ODMwMTc4MDkwCm9mZnNldDogLTI1MjAwMDAwCg\"",
         "id": "5659864350964438352",
         "kind": "blogger#post",
         "published": "2022-06-09T20:02:00-07:00",
         "replies": {
            "selfLink": "https://www.googleapis.com/blogger/v3/blogs/8097677691848866160/posts/5659864350964438352/comments",
            "totalItems": "0"
         },
         "selfLink": "https://www.googleapis.com/blogger/v3/blogs/8097677691848866160/posts/5659864350964438352",
         "title": "Preemptive war",
         "updated": "2022-06-09T20:02:58-07:00",
         "url": "http://militarconceptoswiki.blogspot.com/2022/06/preemptive-war.html"
      },
      {
         "author": {
            "displayName": "Ray",
            "id": "15300513361551186188",
            "image": {
               "url": "//www.blogger.com/img/blogger_logo_round_35.png"
            },
            "url": "https://www.blogger.com/profile/15300513361551186188"
         },
         "blog": {
            "id": "8097677691848866160"
         },
         "content": "",
         "etag": "\"dGltZXN0YW1wOiAxNjU0ODMwMTA5NDE3Cm9mZnNldDogLTI1MjAwMDAwCg\"",
         "id": "4828764946617927943",
         "kind": "blogger#post",
         "published": "2022-06-09T20:01:00-07:00",
         "replies": {
            "selfLink": "https://www.googleapis.com/blogger/v3/blogs/8097677691848866160/posts/4828764946617927943/comments",
            "totalItems": "0"
         },
         "selfLink": "https://www.googleapis.com/blogger/v3/blogs/8097677691848866160/posts/4828764946617927943",
         "title": "Electronic countemeasure",
         "updated": "2022-06-09T20:01:49-07:00",
         "url": "http://militarconceptoswiki.blogspot.com/2022/06/electronic-countemeasure.html"
      },
      {
         "author": {
            "displayName": "Ray",
            "id": "15300513361551186188",
            "image": {
               "url": "//www.blogger.com/img/blogger_logo_round_35.png"
            },
            "url": "https://www.blogger.com/profile/15300513361551186188"
         },
         "blog": {
            "id": "8097677691848866160"
         },
         "content": "",
         "etag": "\"dGltZXN0YW1wOiAxNjU0ODI5OTI3NDI3Cm9mZnNldDogLTI1MjAwMDAwCg\"",
         "id": "4710786903033832930",
         "kind": "blogger#post",
         "published": "2022-06-09T19:58:00-07:00",
         "replies": {
            "selfLink": "https://www.googleapis.com/blogger/v3/blogs/8097677691848866160/posts/4710786903033832930/comments",
            "totalItems": "0"
         },
         "selfLink": "https://www.googleapis.com/blogger/v3/blogs/8097677691848866160/posts/4710786903033832930",
         "title": "Defence in depth",
         "updated": "2022-06-09T19:58:47-07:00",
         "url": "http://militarconceptoswiki.blogspot.com/2022/06/defence-in-depth.html"
      },
      {
         "author": {
            "displayName": "Ray",
            "id": "15300513361551186188",
            "image": {
               "url": "//www.blogger.com/img/blogger_logo_round_35.png"
            },
            "url": "https://www.blogger.com/profile/15300513361551186188"
         },
         "blog": {
            "id": "8097677691848866160"
         },
         "content": "",
         "etag": "\"dGltZXN0YW1wOiAxNjU0ODI5ODczNDA3Cm9mZnNldDogLTI1MjAwMDAwCg\"",
         "id": "1612711991634000925",
         "kind": "blogger#post",
         "published": "2022-06-09T19:57:00-07:00",
         "replies": {
            "selfLink": "https://www.googleapis.com/blogger/v3/blogs/8097677691848866160/posts/1612711991634000925/comments",
            "totalItems": "0"
         },
         "selfLink": "https://www.googleapis.com/blogger/v3/blogs/8097677691848866160/posts/1612711991634000925",
         "title": "Phalanx",
         "updated": "2022-06-09T19:57:53-07:00",
         "url": "http://militarconceptoswiki.blogspot.com/2022/06/phalanx.html"
      },
      {
         "author": {
            "displayName": "Ray",
            "id": "15300513361551186188",
            "image": {
               "url": "//www.blogger.com/img/blogger_logo_round_35.png"
            },
            "url": "https://www.blogger.com/profile/15300513361551186188"
         },
         "blog": {
            "id": "8097677691848866160"
         },
         "content": "",
         "etag": "\"dGltZXN0YW1wOiAxNjU0ODI5Nzc1MDM2Cm9mZnNldDogLTI1MjAwMDAwCg\"",
         "id": "6085668362264345735",
         "kind": "blogger#post",
         "published": "2022-06-09T19:56:00-07:00",
         "replies": {
            "selfLink": "https://www.googleapis.com/blogger/v3/blogs/8097677691848866160/posts/6085668362264345735/comments",
            "totalItems": "0"
         },
         "selfLink": "https://www.googleapis.com/blogger/v3/blogs/8097677691848866160/posts/6085668362264345735",
         "title": "All round defence",
         "updated": "2022-06-09T19:56:15-07:00",
         "url": "http://militarconceptoswiki.blogspot.com/2022/06/all-round-defence.html"
      },
      {
         "author": {
            "displayName": "Ray",
            "id": "15300513361551186188",
            "image": {
               "url": "//www.blogger.com/img/blogger_logo_round_35.png"
            },
            "url": "https://www.blogger.com/profile/15300513361551186188"
         },
         "blog": {
            "id": "8097677691848866160"
         },
         "content": "",
         "etag": "\"dGltZXN0YW1wOiAxNjU0ODI5NzE4NTk2Cm9mZnNldDogLTI1MjAwMDAwCg\"",
         "id": "8197248610491832802",
         "kind": "blogger#post",
         "published": "2022-06-09T19:55:00-07:00",
         "replies": {
            "selfLink": "https://www.googleapis.com/blogger/v3/blogs/8097677691848866160/posts/8197248610491832802/comments",
            "totalItems": "0"
         },
         "selfLink": "https://www.googleapis.com/blogger/v3/blogs/8097677691848866160/posts/8197248610491832802",
         "title": "Scroched earth",
         "updated": "2022-06-09T19:55:18-07:00",
         "url": "http://militarconceptoswiki.blogspot.com/2022/06/scroched-earth.html"
      },
      {
         "author": {
            "displayName": "Ray",
            "id": "15300513361551186188",
            "image": {
               "url": "//www.blogger.com/img/blogger_logo_round_35.png"
            },
            "url": "https://www.blogger.com/profile/15300513361551186188"
         },
         "blog": {
            "id": "8097677691848866160"
         },
         "content": "",
         "etag": "\"dGltZXN0YW1wOiAxNjU0ODI5NTY4MjA2Cm9mZnNldDogLTI1MjAwMDAwCg\"",
         "id": "577735064259078512",
         "kind": "blogger#post",
         "published": "2022-06-09T19:52:00-07:00",
         "replies": {
            "selfLink": "https://www.googleapis.com/blogger/v3/blogs/8097677691848866160/posts/577735064259078512/comments",
            "totalItems": "0"
         },
         "selfLink": "https://www.googleapis.com/blogger/v3/blogs/8097677691848866160/posts/577735064259078512",
         "title": "Counterattack",
         "updated": "2022-06-09T19:52:48-07:00",
         "url": "http://militarconceptoswiki.blogspot.com/2022/06/counterattack.html"
      },
      {
         "author": {
            "displayName": "Ray",
            "id": "15300513361551186188",
            "image": {
               "url": "//www.blogger.com/img/blogger_logo_round_35.png"
            },
            "url": "https://www.blogger.com/profile/15300513361551186188"
         },
         "blog": {
            "id": "8097677691848866160"
         },
         "content": "",
         "etag": "\"dGltZXN0YW1wOiAxNjU0ODI5NTExMTY5Cm9mZnNldDogLTI1MjAwMDAwCg\"",
         "id": "1775754740433802918",
         "kind": "blogger#post",
         "published": "2022-06-09T19:51:00-07:00",
         "replies": {
            "selfLink": "https://www.googleapis.com/blogger/v3/blogs/8097677691848866160/posts/1775754740433802918/comments",
            "totalItems": "0"
         },
         "selfLink": "https://www.googleapis.com/blogger/v3/blogs/8097677691848866160/posts/1775754740433802918",
         "title": "Breakout (military)",
         "updated": "2022-06-09T19:51:51-07:00",
         "url": "http://militarconceptoswiki.blogspot.com/2022/06/breakout-military.html"
      },
      {
         "author": {
            "displayName": "Ray",
            "id": "15300513361551186188",
            "image": {
               "url": "//www.blogger.com/img/blogger_logo_round_35.png"
            },
            "url": "https://www.blogger.com/profile/15300513361551186188"
         },
         "blog": {
            "id": "8097677691848866160"
         },
         "content": "",
         "etag": "\"dGltZXN0YW1wOiAxNjU0ODI5NDU2Njc5Cm9mZnNldDogLTI1MjAwMDAwCg\"",
         "id": "2453875701337970926",
         "kind": "blogger#post",
         "published": "2022-06-09T19:50:00-07:00",
         "replies": {
            "selfLink": "https://www.googleapis.com/blogger/v3/blogs/8097677691848866160/posts/2453875701337970926/comments",
            "totalItems": "0"
         },
         "selfLink": "https://www.googleapis.com/blogger/v3/blogs/8097677691848866160/posts/2453875701337970926",
         "title": "Hedgehog defence",
         "updated": "2022-06-09T19:50:56-07:00",
         "url": "http://militarconceptoswiki.blogspot.com/2022/06/hedgehog-defence.html"
      },
      {
         "author": {
            "displayName": "Ray",
            "id": "15300513361551186188",
            "image": {
               "url": "//www.blogger.com/img/blogger_logo_round_35.png"
            },
            "url": "https://www.blogger.com/profile/15300513361551186188"
         },
         "blog": {
            "id": "8097677691848866160"
         },
         "content": "",
         "etag": "\"dGltZXN0YW1wOiAxNjU0NzY5MTg2MzM3Cm9mZnNldDogLTI1MjAwMDAwCg\"",
         "id": "2327870992046622213",
         "kind": "blogger#post",
         "published": "2022-06-09T03:06:00-07:00",
         "replies": {
            "selfLink": "https://www.googleapis.com/blogger/v3/blogs/8097677691848866160/posts/2327870992046622213/comments",
            "totalItems": "0"
         },
         "selfLink": "https://www.googleapis.com/blogger/v3/blogs/8097677691848866160/posts/2327870992046622213",
         "title": "Pakfront",
         "updated": "2022-06-09T03:06:26-07:00",
         "url": "http://militarconceptoswiki.blogspot.com/2022/06/pakfront.html"
      },
      {
         "author": {
            "displayName": "Ray",
            "id": "15300513361551186188",
            "image": {
               "url": "//www.blogger.com/img/blogger_logo_round_35.png"
            },
            "url": "https://www.blogger.com/profile/15300513361551186188"
         },
         "blog": {
            "id": "8097677691848866160"
         },
         "content": "",
         "etag": "\"dGltZXN0YW1wOiAxNjU0NzY5MTQyMTQyCm9mZnNldDogLTI1MjAwMDAwCg\"",
         "id": "1518047071988978067",
         "kind": "blogger#post",
         "published": "2022-06-09T03:05:00-07:00",
         "replies": {
            "selfLink": "https://www.googleapis.com/blogger/v3/blogs/8097677691848866160/posts/1518047071988978067/comments",
            "totalItems": "0"
         },
         "selfLink": "https://www.googleapis.com/blogger/v3/blogs/8097677691848866160/posts/1518047071988978067",
         "title": "Deception",
         "updated": "2022-06-09T03:05:42-07:00",
         "url": "http://militarconceptoswiki.blogspot.com/2022/06/deception.html"
      },
      {
         "author": {
            "displayName": "Ray",
            "id": "15300513361551186188",
            "image": {
               "url": "//www.blogger.com/img/blogger_logo_round_35.png"
            },
            "url": "https://www.blogger.com/profile/15300513361551186188"
         },
         "blog": {
            "id": "8097677691848866160"
         },
         "content": "",
         "etag": "\"dGltZXN0YW1wOiAxNjU0NzY5MDQzNDc4Cm9mZnNldDogLTI1MjAwMDAwCg\"",
         "id": "2625678145582122068",
         "kind": "blogger#post",
         "published": "2022-06-09T03:04:00-07:00",
         "replies": {
            "selfLink": "https://www.googleapis.com/blogger/v3/blogs/8097677691848866160/posts/2625678145582122068/comments",
            "totalItems": "0"
         },
         "selfLink": "https://www.googleapis.com/blogger/v3/blogs/8097677691848866160/posts/2625678145582122068",
         "title": "Feint",
         "updated": "2022-06-09T03:04:03-07:00",
         "url": "http://militarconceptoswiki.blogspot.com/2022/06/feint.html"
      },
      {
         "author": {
            "displayName": "Ray",
            "id": "15300513361551186188",
            "image": {
               "url": "//www.blogger.com/img/blogger_logo_round_35.png"
            },
            "url": "https://www.blogger.com/profile/15300513361551186188"
         },
         "blog": {
            "id": "8097677691848866160"
         },
         "content": "",
         "etag": "\"dGltZXN0YW1wOiAxNjU0NzY4OTgyNDI4Cm9mZnNldDogLTI1MjAwMDAwCg\"",
         "id": "3649753676760435738",
         "kind": "blogger#post",
         "published": "2022-06-09T03:03:00-07:00",
         "replies": {
            "selfLink": "https://www.googleapis.com/blogger/v3/blogs/8097677691848866160/posts/3649753676760435738/comments",
            "totalItems": "0"
         },
         "selfLink": "https://www.googleapis.com/blogger/v3/blogs/8097677691848866160/posts/3649753676760435738",
         "title": "Perdify",
         "updated": "2022-06-09T03:03:02-07:00",
         "url": "http://militarconceptoswiki.blogspot.com/2022/06/perdify.html"
      },
      {
         "author": {
            "displayName": "Ray",
            "id": "15300513361551186188",
            "image": {
               "url": "//www.blogger.com/img/blogger_logo_round_35.png"
            },
            "url": "https://www.blogger.com/profile/15300513361551186188"
         },
         "blog": {
            "id": "8097677691848866160"
         },
         "content": "",
         "etag": "\"dGltZXN0YW1wOiAxNjU0NzY4OTI4NzIxCm9mZnNldDogLTI1MjAwMDAwCg\"",
         "id": "5587976059728601162",
         "kind": "blogger#post",
         "published": "2022-06-09T03:02:00-07:00",
         "replies": {
            "selfLink": "https://www.googleapis.com/blogger/v3/blogs/8097677691848866160/posts/5587976059728601162/comments",
            "totalItems": "0"
         },
         "selfLink": "https://www.googleapis.com/blogger/v3/blogs/8097677691848866160/posts/5587976059728601162",
         "title": "False flag",
         "updated": "2022-06-09T03:02:08-07:00",
         "url": "http://militarconceptoswiki.blogspot.com/2022/06/false-flag.html"
      },
      {
         "author": {
            "displayName": "Ray",
            "id": "15300513361551186188",
            "image": {
               "url": "//www.blogger.com/img/blogger_logo_round_35.png"
            },
            "url": "https://www.blogger.com/profile/15300513361551186188"
         },
         "blog": {
            "id": "8097677691848866160"
         },
         "content": "",
         "etag": "\"dGltZXN0YW1wOiAxNjU0NzY4ODQyNzA0Cm9mZnNldDogLTI1MjAwMDAwCg\"",
         "id": "8239738019513234915",
         "kind": "blogger#post",
         "published": "2022-06-09T03:00:00-07:00",
         "replies": {
            "selfLink": "https://www.googleapis.com/blogger/v3/blogs/8097677691848866160/posts/8239738019513234915/comments",
            "totalItems": "0"
         },
         "selfLink": "https://www.googleapis.com/blogger/v3/blogs/8097677691848866160/posts/8239738019513234915",
         "title": "Military camouflage",
         "updated": "2022-06-09T03:00:42-07:00",
         "url": "http://militarconceptoswiki.blogspot.com/2022/06/military-camouflage.html"
      },
      {
         "author": {
            "displayName": "Ray",
            "id": "15300513361551186188",
            "image": {
               "url": "//www.blogger.com/img/blogger_logo_round_35.png"
            },
            "url": "https://www.blogger.com/profile/15300513361551186188"
         },
         "blog": {
            "id": "8097677691848866160"
         },
         "content": "",
         "etag": "\"dGltZXN0YW1wOiAxNjU0NzY4NzQ1ODE1Cm9mZnNldDogLTI1MjAwMDAwCg\"",
         "id": "8639009798963281213",
         "kind": "blogger#post",
         "published": "2022-06-09T02:59:00-07:00",
         "replies": {
            "selfLink": "https://www.googleapis.com/blogger/v3/blogs/8097677691848866160/posts/8639009798963281213/comments",
            "totalItems": "0"
         },
         "selfLink": "https://www.googleapis.com/blogger/v3/blogs/8097677691848866160/posts/8639009798963281213",
         "title": "Disinformation",
         "updated": "2022-06-09T02:59:05-07:00",
         "url": "http://militarconceptoswiki.blogspot.com/2022/06/disinformation.html"
      },
      {
         "author": {
            "displayName": "Ray",
            "id": "15300513361551186188",
            "image": {
               "url": "//www.blogger.com/img/blogger_logo_round_35.png"
            },
            "url": "https://www.blogger.com/profile/15300513361551186188"
         },
         "blog": {
            "id": "8097677691848866160"
         },
         "content": "",
         "etag": "\"dGltZXN0YW1wOiAxNjU0NzY4NjY2NzMzCm9mZnNldDogLTI1MjAwMDAwCg\"",
         "id": "2834187853366403456",
         "kind": "blogger#post",
         "published": "2022-06-09T02:57:00-07:00",
         "replies": {
            "selfLink": "https://www.googleapis.com/blogger/v3/blogs/8097677691848866160/posts/2834187853366403456/comments",
            "totalItems": "0"
         },
         "selfLink": "https://www.googleapis.com/blogger/v3/blogs/8097677691848866160/posts/2834187853366403456",
         "title": "Irregular military",
         "updated": "2022-06-09T02:57:46-07:00",
         "url": "http://militarconceptoswiki.blogspot.com/2022/06/irregular-military.html"
      },
      {
         "author": {
            "displayName": "Ray",
            "id": "15300513361551186188",
            "image": {
               "url": "//www.blogger.com/img/blogger_logo_round_35.png"
            },
            "url": "https://www.blogger.com/profile/15300513361551186188"
         },
         "blog": {
            "id": "8097677691848866160"
         },
         "content": "",
         "etag": "\"dGltZXN0YW1wOiAxNjU0NzY4NTgzNTk5Cm9mZnNldDogLTI1MjAwMDAwCg\"",
         "id": "7753344294066042773",
         "kind": "blogger#post",
         "published": "2022-06-09T02:56:00-07:00",
         "replies": {
            "selfLink": "https://www.googleapis.com/blogger/v3/blogs/8097677691848866160/posts/7753344294066042773/comments",
            "totalItems": "0"
         },
         "selfLink": "https://www.googleapis.com/blogger/v3/blogs/8097677691848866160/posts/7753344294066042773",
         "title": "Hit and run tactics",
         "updated": "2022-06-09T02:56:23-07:00",
         "url": "http://militarconceptoswiki.blogspot.com/2022/06/hit-and-run-tactics.html"
      },
      {
         "author": {
            "displayName": "Ray",
            "id": "15300513361551186188",
            "image": {
               "url": "//www.blogger.com/img/blogger_logo_round_35.png"
            },
            "url": "https://www.blogger.com/profile/15300513361551186188"
         },
         "blog": {
            "id": "8097677691848866160"
         },
         "content": "",
         "etag": "\"dGltZXN0YW1wOiAxNjU0NzY4NTI5MTc4Cm9mZnNldDogLTI1MjAwMDAwCg\"",
         "id": "6705649377018496038",
         "kind": "blogger#post",
         "published": "2022-06-09T02:55:00-07:00",
         "replies": {
            "selfLink": "https://www.googleapis.com/blogger/v3/blogs/8097677691848866160/posts/6705649377018496038/comments",
            "totalItems": "0"
         },
         "selfLink": "https://www.googleapis.com/blogger/v3/blogs/8097677691848866160/posts/6705649377018496038",
         "title": "Parthian shot",
         "updated": "2022-06-09T02:55:29-07:00",
         "url": "http://militarconceptoswiki.blogspot.com/2022/06/parthian-shot.html"
      }
   ],
   "kind": "blogger#postList"
}
